{
  "db_name": "PostgreSQL",
  "query": "\n            SELECT * FROM \"Genre\"\n            WHERE id = $1 AND deleted_at IS NULL\n            ",
  "describe": {
    "columns": [
      {
        "ordinal": 0,
        "name": "id",
        "type_info": "Int8"
      },
      {
        "ordinal": 1,
        "name": "name",
        "type_info": "Text"
      },
      {
        "ordinal": 2,
        "name": "color",
        "type_info": "Text"
      },
      {
        "ordinal": 3,
        "name": "created_at",
        "type_info": "Timestamptz"
      },
      {
        "ordinal": 4,
        "name": "edited_at",
        "type_info": "Timestamptz"
      },
      {
        "ordinal": 5,
        "name": "deleted_at",
        "type_info": "Timestamptz"
      }
    ],
    "parameters": {
      "Left": [
        "Int8"
      ]
    },
    "nullable": [
      false,
      false,
      false,
      false,
      false,
      true
    ]
  },
  "hash": "7626170f3f33c6b597f59af464cc8c506c2a20e2326d647b41b435ec050a52fd"
}
