{
  "db_name": "PostgreSQL",
  "query": "\n                SELECT * FROM \"Rating\"\n                WHERE audiobook_id = $1 AND deleted_at IS NULL\n                ",
  "describe": {
    "columns": [
      {
        "ordinal": 0,
        "name": "id",
        "type_info": "Int8"
      },
      {
        "ordinal": 1,
        "name": "user_id",
        "type_info": "Int8"
      },
      {
        "ordinal": 2,
        "name": "audiobook_id",
        "type_info": "Int8"
      },
      {
        "ordinal": 3,
        "name": "rating",
        "type_info": "Int2"
      },
      {
        "ordinal": 4,
        "name": "review",
        "type_info": "Text"
      },
      {
        "ordinal": 5,
        "name": "created_at",
        "type_info": "Timestamptz"
      },
      {
        "ordinal": 6,
        "name": "edited_at",
        "type_info": "Timestamptz"
      },
      {
        "ordinal": 7,
        "name": "deleted_at",
        "type_info": "Timestamptz"
      }
    ],
    "parameters": {
      "Left": [
        "Int8"
      ]
    },
    "nullable": [
      false,
      false,
      false,
      false,
      true,
      false,
      false,
      true
    ]
  },
  "hash": "6666c4dbcebafece53c250efdb9ceb1e6060fbd2dd691c5c35267167aec22c0a"
}
